gpie/__init__.py
gpie/base.py
gpie/infer/__init__.py
gpie/infer/densities.py
gpie/infer/mcmc.py
gpie/infer/optimizer.py
gpie/infer/variational.py
gpie/kernel/__init__.py
gpie/kernel/bayes_optimizer.py
gpie/kernel/gaussian_process.py
gpie/kernel/kernels.py
gpie/kernel/means.py
gpie/linalg/__init__.py
gpie/linalg/linalg.py
gpie/metric/__init__.py
gpie/metric/metrics.py
gpie/util/__init__.py
gpie/util/context.py
gpie/util/data.py
gpie-0.2.2.dist-info/LICENSE
gpie-0.2.2.dist-info/METADATA
gpie-0.2.2.dist-info/WHEEL
gpie-0.2.2.dist-info/top_level.txt
gpie-0.2.2.dist-info/RECORD
