Metadata-Version: 2.1
Name: gpie
Version: 0.2.2
Summary: GPie: Gaussian Process tiny explorer
Home-page: https://github.com/zack-x-zhang/gpie
Author: Zack Zhang
Author-email: zack.zhang.coder@gmail.com
License: UNKNOWN
Platform: any
Classifier: Topic :: Scientific/Engineering
Classifier: Programming Language :: Python :: 3
Requires-Python: >=3.6
Requires-Dist: numpy (>=1.18)
Requires-Dist: scipy (>=1.4)
